execution_logger/__init__.py
execution_logger/execution_logger.py
execution_logger-1.1.9.dist-info/METADATA
execution_logger-1.1.9.dist-info/WHEEL
execution_logger-1.1.9.dist-info/top_level.txt
execution_logger-1.1.9.dist-info/RECORD
