Metadata-Version: 2.4
Name: execution-logger
Version: 1.1.9
Summary: A comprehensive Python logging solution with Microsoft SharePoint and Dataverse integration
Home-page: https://github.com/The-Fruit-People/execution-logger
Author: Rizwana
Author-email: rizwana@thefruitpeople.ie
Classifier: Development Status :: 4 - Beta
Classifier: Intended Audience :: Developers
Classifier: Intended Audience :: System Administrators
Classifier: Programming Language :: Python :: 3
Classifier: License :: OSI Approved :: MIT License
Classifier: Operating System :: OS Independent
Classifier: Topic :: System :: Logging
Classifier: Topic :: System :: Monitoring
Requires-Python: >=3.11
Requires-Dist: msal>=1.20.0
Requires-Dist: requests>=2.28.0
Dynamic: author
Dynamic: author-email
Dynamic: classifier
Dynamic: description
Dynamic: description-content-type
Dynamic: home-page
Dynamic: requires-dist
Dynamic: requires-python
Dynamic: summary
